{
  "stats": {
    "userProfileId": 58868684,
    "totalKilocalories": 2450.0,
    "activeKilocalories": 466.0,
    "bmrKilocalories": 1984.0,
    "wellnessKilocalories": 2450.0,
    "burnedKilocalories": null,
    "consumedKilocalories": null,
    "remainingKilocalories": null,
    "totalSteps": 6289,
    "netCalorieGoal": null,
    "totalDistanceMeters": 5225,
    "wellnessDistanceMeters": 5225,
    "wellnessActiveKilocalories": 466.0,
    "netRemainingKilocalories": 466.0,
    "userDailySummaryId": 58868684,
    "calendarDate": "2025-05-08",
    "rule": {
      "typeId": 4,
      "typeKey": "groups"
    },
    "uuid": "b33663fa6c744ccc956f3ed82bcd85dc",
    "dailyStepGoal": 7850,
    "wellnessStartTimeGmt": "2025-05-07T21:00:00.0",
    "wellnessStartTimeLocal": "2025-05-08T00:00:00.0",
    "wellnessEndTimeGmt": "2025-05-08T21:00:00.0",
    "wellnessEndTimeLocal": "2025-05-09T00:00:00.0",
    "durationInMilliseconds": 86400000,
    "wellnessDescription": null,
    "highlyActiveSeconds": 3208,
    "activeSeconds": 4306,
    "sedentarySeconds": 49623,
    "sleepingSeconds": 29263,
    "includesWellnessData": true,
    "includesActivityData": false,
    "includesCalorieConsumedData": false,
    "privacyProtected": false,
    "moderateIntensityMinutes": 10,
    "vigorousIntensityMinutes": 10,
    "floorsAscendedInMeters": 0.0,
    "floorsDescendedInMeters": 24.974,
    "floorsAscended": 0.0,
    "floorsDescended": 8.19357,
    "intensityMinutesGoal": 150,
    "userFloorsAscendedGoal": 10,
    "minHeartRate": 49,
    "maxHeartRate": 158,
    "restingHeartRate": 56,
    "lastSevenDaysAvgRestingHeartRate": 57,
    "source": "GARMIN",
    "averageStressLevel": 35,
    "maxStressLevel": 99,
    "stressDuration": 37140,
    "restStressDuration": 34740,
    "activityStressDuration": 8220,
    "uncategorizedStressDuration": 3000,
    "totalStressDuration": 83100,
    "lowStressDuration": 18540,
    "mediumStressDuration": 13620,
    "highStressDuration": 4980,
    "stressPercentage": 44.69,
    "restStressPercentage": 41.81,
    "activityStressPercentage": 9.89,
    "uncategorizedStressPercentage": 3.61,
    "lowStressPercentage": 22.31,
    "mediumStressPercentage": 16.39,
    "highStressPercentage": 5.99,
    "stressQualifier": "BALANCED",
    "measurableAwakeDuration": 51000,
    "measurableAsleepDuration": 29100,
    "lastSyncTimestampGMT": null,
    "minAvgHeartRate": 51,
    "maxAvgHeartRate": 157,
    "bodyBatteryChargedValue": 67,
    "bodyBatteryDrainedValue": 56,
    "bodyBatteryHighestValue": 68,
    "bodyBatteryLowestValue": 5,
    "bodyBatteryMostRecentValue": 16,
    "bodyBatteryDuringSleep": 63,
    "bodyBatteryAtWakeTime": 68,
    "bodyBatteryVersion": 3.0,
    "abnormalHeartRateAlertsCount": null,
    "averageSpo2": null,
    "lowestSpo2": null,
    "latestSpo2": null,
    "latestSpo2ReadingTimeGmt": null,
    "latestSpo2ReadingTimeLocal": null,
    "averageMonitoringEnvironmentAltitude": 128.0,
    "restingCaloriesFromActivity": null,
    "bodyBatteryDynamicFeedbackEvent": {
      "eventTimestampGmt": "2025-05-08T19:50:44",
      "bodyBatteryLevel": "MODERATE",
      "feedbackShortType": "SLEEP_PREPARATION_STRESSFUL_AND_INACTIVE",
      "feedbackLongType": "SLEEP_PREPARATION_STRESSFUL_AND_INACTIVE"
    },
    "endOfDayBodyBatteryDynamicFeedbackEvent": {
      "eventTimestampGmt": "2025-05-07T23:42:40",
      "bodyBatteryLevel": "HIGH",
      "feedbackShortType": "SLEEP_TIME_PASSED_STRESSFUL_AND_INACTIVE",
      "feedbackLongType": "SLEEP_TIME_PASSED_STRESSFUL_AND_INACTIVE"
    },
    "bodyBatteryActivityEventList": [
      {
        "eventType": "SLEEP",
        "eventStartTimeGmt": "2025-05-07T20:19:15",
        "timezoneOffset": 10800000,
        "durationInMilliseconds": 31620000,
        "bodyBatteryImpact": 63,
        "feedbackType": "NONE",
        "shortFeedback": "NONE",
        "deviceId": 3404099129,
        "activityName": null,
        "activityType": null,
        "activityId": null,
        "eventUpdateTimeGmt": "2025-05-08T06:01:32"
      }
    ],
    "avgWakingRespirationValue": 14.0,
    "highestRespirationValue": 22.0,
    "lowestRespirationValue": 7.0,
    "latestRespirationValue": 16.0,
    "latestRespirationTimeGMT": "2025-05-08T20:59:00.0",
    "respirationAlgorithmVersion": 200
  },
  "steps": [
    {
      "startGMT": "2025-05-07T21:00:00.0",
      "endGMT": "2025-05-07T21:15:00.0",
      "steps": 0,
      "pushes": 0,
      "primaryActivityLevel": "none",
      "activityLevelConstant": true
    },
    {
      "startGMT": "2025-05-07T21:15:00.0",
      "endGMT": "2025-05-07T21:30:00.0",
      "steps": 0,
      "pushes": 0,
      "primaryActivityLevel": "none",
      "activityLevelConstant": true
    },
    {
      "startGMT": "2025-05-07T21:30:00.0",
      "endGMT": "2025-05-07T21:45:00.0",
      "steps": 0,
      "pushes": 0,
      "primaryActivityLevel": "none",
      "activityLevelConstant": true
    },
    {
      "startGMT": "2025-05-07T21:45:00.0",
      "endGMT": "2025-05-07T22:00:00.0",
      "steps": 0,
      "pushes": 0,
      "primaryActivityLevel": "none",
      "activityLevelConstant": true
    },
    {
      "startGMT": "2025-05-07T22:00:00.0",
      "endGMT": "2025-05-07T22:15:00.0",
      "steps": 0,
      "pushes": 0,
      "primaryActivityLevel": "none",
      "activityLevelConstant": true
    },
    {
      "startGMT": "2025-05-07T22:15:00.0",
      "endGMT": "2025-05-07T22:30:00.0",
      "steps": 0,
      "pushes": 0,
      "primaryActivityLevel": "none",
      "activityLevelConstant": true
    },
    {
      "startGMT": "2025-05-07T22:30:00.0",
      "endGMT": "2025-05-07T22:45:00.0",
      "steps": 0,
      "pushes": 0,
      "primaryActivityLevel": "none",
      "activityLevelConstant": true
    },
    {
      "startGMT": "2025-05-07T22:45:00.0",
      "endGMT": "2025-05-07T23:00:00.0",
      "steps": 0,
      "pushes": 0,
      "primaryActivityLevel": "none",
      "activityLevelConstant": true
    },
    {
      "startGMT": "2025-05-07T23:00:00.0",
      "endGMT": "2025-05-07T23:15:00.0",
      "steps": 0,
      "pushes": 0,
      "primaryActivityLevel": "none",
      "activityLevelConstant": true
    },
    {
      "startGMT": "2025-05-07T23:15:00.0",
      "endGMT": "2025-05-07T23:30:00.0",
      "steps": 0,
      "pushes": 0,
      "primaryActivityLevel": "none",
      "activityLevelConstant": true
    },
    {
      "startGMT": "2025-05-07T23:30:00.0",
      "endGMT": "2025-05-07T23:45:00.0",
      "steps": 0,
      "pushes": 0,
      "primaryActivityLevel": "none",
      "activityLevelConstant": true
    },
    {
      "startGMT": "2025-05-07T23:45:00.0",
      "endGMT": "2025-05-08T00:00:00.0",
      "steps": 0,
      "pushes": 0,
      "primaryActivityLevel": "none",
      "activityLevelConstant": true
    },
    {
      "startGMT": "2025-05-08T00:00:00.0",
      "endGMT": "2025-05-08T00:15:00.0",
      "steps": 0,
      "pushes": 0,
      "primaryActivityLevel": "none",
      "activityLevelConstant": true
    },
    {
      "startGMT": "2025-05-08T00:15:00.0",
      "endGMT": "2025-05-08T00:30:00.0",
      "steps": 0,
      "pushes": 0,
      "primaryActivityLevel": "none",
      "activityLevelConstant": true
    },
    {
      "startGMT": "2025-05-08T00:30:00.0",
      "endGMT": "2025-05-08T00:45:00.0",
      "steps": 0,
      "pushes": 0,
      "primaryActivityLevel": "none",
      "activityLevelConstant": true
    },
    {
      "startGMT": "2025-05-08T00:45:00.0",
      "endGMT": "2025-05-08T01:00:00.0",
      "steps": 0,
      "pushes": 0,
      "primaryActivityLevel": "none",
      "activityLevelConstant": true
    },
    {
      "startGMT": "2025-05-08T01:00:00.0",
      "endGMT": "2025-05-08T01:15:00.0",
      "steps": 0,
      "pushes": 0,
      "primaryActivityLevel": "none",
      "activityLevelConstant": true
    },
    {
      "startGMT": "2025-05-08T01:15:00.0",
      "endGMT": "2025-05-08T01:30:00.0",
      "steps": 0,
      "pushes": 0,
      "primaryActivityLevel": "none",
      "activityLevelConstant": true
    },
    {
      "startGMT": "2025-05-08T01:30:00.0",
      "endGMT": "2025-05-08T01:45:00.0",
      "steps": 0,
      "pushes": 0,
      "primaryActivityLevel": "none",
      "activityLevelConstant": true
    },
    {
      "startGMT": "2025-05-08T01:45:00.0",
      "endGMT": "2025-05-08T02:00:00.0",
      "steps": 0,
      "pushes": 0,
      "primaryActivityLevel": "none",
      "activityLevelConstant": true
    },
    {
      "startGMT": "2025-05-08T02:00:00.0",
      "endGMT": "2025-05-08T02:15:00.0",
      "steps": 0,
      "pushes": 0,
      "primaryActivityLevel": "none",
      "activityLevelConstant": true
    },
    {
      "startGMT": "2025-05-08T02:15:00.0",
      "endGMT": "2025-05-08T02:30:00.0",
      "steps": 0,
      "pushes": 0,
      "primaryActivityLevel": "none",
      "activityLevelConstant": true
    },
    {
      "startGMT": "2025-05-08T02:30:00.0",
      "endGMT": "2025-05-08T02:45:00.0",
      "steps": 0,
      "pushes": 0,
      "primaryActivityLevel": "none",
      "activityLevelConstant": true
    },
    {
      "startGMT": "2025-05-08T02:45:00.0",
      "endGMT": "2025-05-08T03:00:00.0",
      "steps": 0,
      "pushes": 0,
      "primaryActivityLevel": "none",
      "activityLevelConstant": true
    },
    {
      "startGMT": "2025-05-08T03:00:00.0",
      "endGMT": "2025-05-08T03:15:00.0",
      "steps": 0,
      "pushes": 0,
      "primaryActivityLevel": "none",
      "activityLevelConstant": true
    },
    {
      "startGMT": "2025-05-08T03:15:00.0",
      "endGMT": "2025-05-08T03:30:00.0",
      "steps": 0,
      "pushes": 0,
      "primaryActivityLevel": "none",
      "activityLevelConstant": true
    },
    {
      "startGMT": "2025-05-08T03:30:00.0",
      "endGMT": "2025-05-08T03:45:00.0",
      "steps": 0,
      "pushes": 0,
      "primaryActivityLevel": "none",
      "activityLevelConstant": true
    },
    {
      "startGMT": "2025-05-08T03:45:00.0",
      "endGMT": "2025-05-08T04:00:00.0",
      "steps": 0,
      "pushes": 0,
      "primaryActivityLevel": "none",
      "activityLevelConstant": true
    },
    {
      "startGMT": "2025-05-08T04:00:00.0",
      "endGMT": "2025-05-08T04:15:00.0",
      "steps": 0,
      "pushes": 0,
      "primaryActivityLevel": "none",
      "activityLevelConstant": true
    },
    {
      "startGMT": "2025-05-08T04:15:00.0",
      "endGMT": "2025-05-08T04:30:00.0",
      "steps": 0,
      "pushes": 0,
      "primaryActivityLevel": "none",
      "activityLevelConstant": true
    },
    {
      "startGMT": "2025-05-08T04:30:00.0",
      "endGMT": "2025-05-08T04:45:00.0",
      "steps": 0,
      "pushes": 0,
      "primaryActivityLevel": "none",
      "activityLevelConstant": true
    },
    {
      "startGMT": "2025-05-08T04:45:00.0",
      "endGMT": "2025-05-08T05:00:00.0",
      "steps": 0,
      "pushes": 0,
      "primaryActivityLevel": "none",
      "activityLevelConstant": true
    },
    {
      "startGMT": "2025-05-08T05:00:00.0",
      "endGMT": "2025-05-08T05:15:00.0",
      "steps": 0,
      "pushes": 0,
      "primaryActivityLevel": "none",
      "activityLevelConstant": true
    },
    {
      "startGMT": "2025-05-08T05:15:00.0",
      "endGMT": "2025-05-08T05:30:00.0",
      "steps": 0,
      "pushes": 0,
      "primaryActivityLevel": "none",
      "activityLevelConstant": true
    },
    {
      "startGMT": "2025-05-08T05:30:00.0",
      "endGMT": "2025-05-08T05:45:00.0",
      "steps": 0,
      "pushes": 0,
      "primaryActivityLevel": "none",
      "activityLevelConstant": true
    },
    {
      "startGMT": "2025-05-08T05:45:00.0",
      "endGMT": "2025-05-08T06:00:00.0",
      "steps": 0,
      "pushes": 0,
      "primaryActivityLevel": "none",
      "activityLevelConstant": true
    },
    {
      "startGMT": "2025-05-08T06:00:00.0",
      "endGMT": "2025-05-08T06:15:00.0",
      "steps": 0,
      "pushes": 0,
      "primaryActivityLevel": "none",
      "activityLevelConstant": true
    },
    {
      "startGMT": "2025-05-08T06:15:00.0",
      "endGMT": "2025-05-08T06:30:00.0",
      "steps": 0,
      "pushes": 0,
      "primaryActivityLevel": "none",
      "activityLevelConstant": true
    },
    {
      "startGMT": "2025-05-08T06:30:00.0",
      "endGMT": "2025-05-08T06:45:00.0",
      "steps": 0,
      "pushes": 0,
      "primaryActivityLevel": "none",
      "activityLevelConstant": true
    },
    {
      "startGMT": "2025-05-08T06:45:00.0",
      "endGMT": "2025-05-08T07:00:00.0",
      "steps": 0,
      "pushes": 0,
      "primaryActivityLevel": "none",
      "activityLevelConstant": true
    },
    {
      "startGMT": "2025-05-08T07:00:00.0",
      "endGMT": "2025-05-08T07:15:00.0",
      "steps": 0,
      "pushes": 0,
      "primaryActivityLevel": "none",
      "activityLevelConstant": true
    },
    {
      "startGMT": "2025-05-08T07:15:00.0",
      "endGMT": "2025-05-08T07:30:00.0",
      "steps": 0,
      "pushes": 0,
      "primaryActivityLevel": "none",
      "activityLevelConstant": true
    },
    {
      "startGMT": "2025-05-08T07:30:00.0",
      "endGMT": "2025-05-08T07:45:00.0",
      "steps": 0,
      "pushes": 0,
      "primaryActivityLevel": "none",
      "activityLevelConstant": true
    },
    {
      "startGMT": "2025-05-08T07:45:00.0",
      "endGMT": "2025-05-08T08:00:00.0",
      "steps": 0,
      "pushes": 0,
      "primaryActivityLevel": "none",
      "activityLevelConstant": true
    },
    {
      "startGMT": "2025-05-08T08:00:00.0",
      "endGMT": "2025-05-08T08:15:00.0",
      "steps": 0,
      "pushes": 0,
      "primaryActivityLevel": "none",
      "activityLevelConstant": true
    },
    {
      "startGMT": "2025-05-08T08:15:00.0",
      "endGMT": "2025-05-08T08:30:00.0",
      "steps": 0,
      "pushes": 0,
      "primaryActivityLevel": "none",
      "activityLevelConstant": true
    },
    {
      "startGMT": "2025-05-08T08:30:00.0",
      "endGMT": "2025-05-08T08:45:00.0",
      "steps": 0,
      "pushes": 0,
      "primaryActivityLevel": "none",
      "activityLevelConstant": true
    },
    {
      "startGMT": "2025-05-08T08:45:00.0",
      "endGMT": "2025-05-08T09:00:00.0",
      "steps": 0,
      "pushes": 0,
      "primaryActivityLevel": "none",
      "activityLevelConstant": true
    },
    {
      "startGMT": "2025-05-08T09:00:00.0",
      "endGMT": "2025-05-08T09:15:00.0",
      "steps": 0,
      "pushes": 0,
      "primaryActivityLevel": "none",
      "activityLevelConstant": true
    },
    {
      "startGMT": "2025-05-08T09:15:00.0",
      "endGMT": "2025-05-08T09:30:00.0",
      "steps": 0,
      "pushes": 0,
      "primaryActivityLevel": "none",
      "activityLevelConstant": true
    },
    {
      "startGMT": "2025-05-08T09:30:00.0",
      "endGMT": "2025-05-08T09:45:00.0",
      "steps": 0,
      "pushes": 0,
      "primaryActivityLevel": "none",
      "activityLevelConstant": true
    },
    {
      "startGMT": "2025-05-08T09:45:00.0",
      "endGMT": "2025-05-08T10:00:00.0",
      "steps": 0,
      "pushes": 0,
      "primaryActivityLevel": "none",
      "activityLevelConstant": true
    },
    {
      "startGMT": "2025-05-08T10:00:00.0",
      "endGMT": "2025-05-08T10:15:00.0",
      "steps": 0,
      "pushes": 0,
      "primaryActivityLevel": "none",
      "activityLevelConstant": true
    },
    {
      "startGMT": "2025-05-08T10:15:00.0",
      "endGMT": "2025-05-08T10:30:00.0",
      "steps": 0,
      "pushes": 0,
      "primaryActivityLevel": "none",
      "activityLevelConstant": true
    },
    {
      "startGMT": "2025-05-08T10:30:00.0",
      "endGMT": "2025-05-08T10:45:00.0",
      "steps": 0,
      "pushes": 0,
      "primaryActivityLevel": "none",
      "activityLevelConstant": true
    },
    {
      "startGMT": "2025-05-08T10:45:00.0",
      "endGMT": "2025-05-08T11:00:00.0",
      "steps": 0,
      "pushes": 0,
      "primaryActivityLevel": "none",
      "activityLevelConstant": true
    },
    {
      "startGMT": "2025-05-08T11:00:00.0",
      "endGMT": "2025-05-08T11:15:00.0",
      "steps": 0,
      "pushes": 0,
      "primaryActivityLevel": "none",
      "activityLevelConstant": true
    },
    {
      "startGMT": "2025-05-08T11:15:00.0",
      "endGMT": "2025-05-08T11:30:00.0",
      "steps": 0,
      "pushes": 0,
      "primaryActivityLevel": "none",
      "activityLevelConstant": true
    },
    {
      "startGMT": "2025-05-08T11:30:00.0",
      "endGMT": "2025-05-08T11:45:00.0",
      "steps": 0,
      "pushes": 0,
      "primaryActivityLevel": "none",
      "activityLevelConstant": true
    },
    {
      "startGMT": "2025-05-08T11:45:00.0",
      "endGMT": "2025-05-08T12:00:00.0",
      "steps": 0,
      "pushes": 0,
      "primaryActivityLevel": "none",
      "activityLevelConstant": true
    },
    {
      "startGMT": "2025-05-08T12:00:00.0",
      "endGMT": "2025-05-08T12:15:00.0",
      "steps": 0,
      "pushes": 0,
      "primaryActivityLevel": "none",
      "activityLevelConstant": true
    },
    {
      "startGMT": "2025-05-08T12:15:00.0",
      "endGMT": "2025-05-08T12:30:00.0",
      "steps": 0,
      "pushes": 0,
      "primaryActivityLevel": "none",
      "activityLevelConstant": true
    },
    {
      "startGMT": "2025-05-08T12:30:00.0",
      "endGMT": "2025-05-08T12:45:00.0",
      "steps": 0,
      "pushes": 0,
      "primaryActivityLevel": "none",
      "activityLevelConstant": true
    },
    {
      "startGMT": "2025-05-08T12:45:00.0",
      "endGMT": "2025-05-08T13:00:00.0",
      "steps": 0,
      "pushes": 0,
      "primaryActivityLevel": "none",
      "activityLevelConstant": true
    },
    {
      "startGMT": "2025-05-08T13:00:00.0",
      "endGMT": "2025-05-08T13:15:00.0",
      "steps": 0,
      "pushes": 0,
      "primaryActivityLevel": "none",
      "activityLevelConstant": true
    },
    {
      "startGMT": "2025-05-08T13:15:00.0",
      "endGMT": "2025-05-08T13:30:00.0",
      "steps": 0,
      "pushes": 0,
      "primaryActivityLevel": "none",
      "activityLevelConstant": true
    },
    {
      "startGMT": "2025-05-08T13:30:00.0",
      "endGMT": "2025-05-08T13:45:00.0",
      "steps": 0,
      "pushes": 0,
      "primaryActivityLevel": "none",
      "activityLevelConstant": true
    },
    {
      "startGMT": "2025-05-08T13:45:00.0",
      "endGMT": "2025-05-08T14:00:00.0",
      "steps": 0,
      "pushes": 0,
      "primaryActivityLevel": "none",
      "activityLevelConstant": true
    },
    {
      "startGMT": "2025-05-08T14:00:00.0",
      "endGMT": "2025-05-08T14:15:00.0",
      "steps": 0,
      "pushes": 0,
      "primaryActivityLevel": "none",
      "activityLevelConstant": true
    },
    {
      "startGMT": "2025-05-08T14:15:00.0",
      "endGMT": "2025-05-08T14:30:00.0",
      "steps": 0,
      "pushes": 0,
      "primaryActivityLevel": "none",
      "activityLevelConstant": true
    },
    {
      "startGMT": "2025-05-08T14:30:00.0",
      "endGMT": "2025-05-08T14:45:00.0",
      "steps": 0,
      "pushes": 0,
      "primaryActivityLevel": "none",
      "activityLevelConstant": true
    },
    {
      "startGMT": "2025-05-08T14:45:00.0",
      "endGMT": "2025-05-08T15:00:00.0",
      "steps": 0,
      "pushes": 0,
      "primaryActivityLevel": "none",
      "activityLevelConstant": true
    },
    {
      "startGMT": "2025-05-08T15:00:00.0",
      "endGMT": "2025-05-08T15:15:00.0",
      "steps": 0,
      "pushes": 0,
      "primaryActivityLevel": "none",
      "activityLevelConstant": true
    },
    {
      "startGMT": "2025-05-08T15:15:00.0",
      "endGMT": "2025-05-08T15:30:00.0",
      "steps": 0,
      "pushes": 0,
      "primaryActivityLevel": "none",
      "activityLevelConstant": true
    },
    {
      "startGMT": "2025-05-08T15:30:00.0",
      "endGMT": "2025-05-08T15:45:00.0",
      "steps": 0,
      "pushes": 0,
      "primaryActivityLevel": "none",
      "activityLevelConstant": true
    },
    {
      "startGMT": "2025-05-08T15:45:00.0",
      "endGMT": "2025-05-08T16:00:00.0",
      "steps": 0,
      "pushes": 0,
      "primaryActivityLevel": "none",
      "activityLevelConstant": true
    },
    {
      "startGMT": "2025-05-08T16:00:00.0",
      "endGMT": "2025-05-08T16:15:00.0",
      "steps": 0,
      "pushes": 0,
      "primaryActivityLevel": "none",
      "activityLevelConstant": true
    },
    {
      "startGMT": "2025-05-08T16:15:00.0",
      "endGMT": "2025-05-08T16:30:00.0",
      "steps": 0,
      "pushes": 0,
      "primaryActivityLevel": "none",
      "activityLevelConstant": true
    },
    {
      "startGMT": "2025-05-08T16:30:00.0",
      "endGMT": "2025-05-08T16:45:00.0",
      "steps": 0,
      "pushes": 0,
      "primaryActivityLevel": "none",
      "activityLevelConstant": true
    },
    {
      "startGMT": "2025-05-08T16:45:00.0",
      "endGMT": "2025-05-08T17:00:00.0",
      "steps": 0,
      "pushes": 0,
      "primaryActivityLevel": "none",
      "activityLevelConstant": true
    },
    {
      "startGMT": "2025-05-08T17:00:00.0",
      "endGMT": "2025-05-08T17:15:00.0",
      "steps": 0,
      "pushes": 0,
      "primaryActivityLevel": "none",
      "activityLevelConstant": true
    },
    {
      "startGMT": "2025-05-08T17:15:00.0",
      "endGMT": "2025-05-08T17:30:00.0",
      "steps": 0,
      "pushes": 0,
      "primaryActivityLevel": "none",
      "activityLevelConstant": true
    },
    {
      "startGMT": "2025-05-08T17:30:00.0",
      "endGMT": "2025-05-08T17:45:00.0",
      "steps": 0,
      "pushes": 0,
      "primaryActivityLevel": "none",
      "activityLevelConstant": true
    },
    {
      "startGMT": "2025-05-08T17:45:00.0",
      "endGMT": "2025-05-08T18:00:00.0",
      "steps": 0,
      "pushes": 0,
      "primaryActivityLevel": "none",
      "activityLevelConstant": true
    },
    {
      "startGMT": "2025-05-08T18:00:00.0",
      "endGMT": "2025-05-08T18:15:00.0",
      "steps": 0,
      "pushes": 0,
      "primaryActivityLevel": "none",
      "activityLevelConstant": true
    },
    {
      "startGMT": "2025-05-08T18:15:00.0",
      "endGMT": "2025-05-08T18:30:00.0",
      "steps": 0,
      "pushes": 0,
      "primaryActivityLevel": "none",
      "activityLevelConstant": true
    },
    {
      "startGMT": "2025-05-08T18:30:00.0",
      "endGMT": "2025-05-08T18:45:00.0",
      "steps": 0,
      "pushes": 0,
      "primaryActivityLevel": "none",
      "activityLevelConstant": true
    },
    {
      "startGMT": "2025-05-08T18:45:00.0",
      "endGMT": "2025-05-08T19:00:00.0",
      "steps": 0,
      "pushes": 0,
      "primaryActivityLevel": "none",
      "activityLevelConstant": true
    },
    {
      "startGMT": "2025-05-08T19:00:00.0",
      "endGMT": "2025-05-08T19:15:00.0",
      "steps": 0,
      "pushes": 0,
      "primaryActivityLevel": "none",
      "activityLevelConstant": true
    },
    {
      "startGMT": "2025-05-08T19:15:00.0",
      "endGMT": "2025-05-08T19:30:00.0",
      "steps": 0,
      "pushes": 0,
      "primaryActivityLevel": "none",
      "activityLevelConstant": true
    },
    {
      "startGMT": "2025-05-08T19:30:00.0",
      "endGMT": "2025-05-08T19:45:00.0",
      "steps": 0,
      "pushes": 0,
      "primaryActivityLevel": "none",
      "activityLevelConstant": true
    },
    {
      "startGMT": "2025-05-08T19:45:00.0",
      "endGMT": "2025-05-08T20:00:00.0",
      "steps": 0,
      "pushes": 0,
      "primaryActivityLevel": "none",
      "activityLevelConstant": true
    },
    {
      "startGMT": "2025-05-08T20:00:00.0",
      "endGMT": "2025-05-08T20:15:00.0",
      "steps": 0,
      "pushes": 0,
      "primaryActivityLevel": "none",
      "activityLevelConstant": true
    },
    {
      "startGMT": "2025-05-08T20:15:00.0",
      "endGMT": "2025-05-08T20:30:00.0",
      "steps": 0,
      "pushes": 0,
      "primaryActivityLevel": "none",
      "activityLevelConstant": true
    },
    {
      "startGMT": "2025-05-08T20:30:00.0",
      "endGMT": "2025-05-08T20:45:00.0",
      "steps": 0,
      "pushes": 0,
      "primaryActivityLevel": "none",
      "activityLevelConstant": true
    }
  ]
}