{
  "userProfilePk": 58868684,
  "hrvSummary": {
    "calendarDate": "2026-01-08",
    "weeklyAvg": 47,
    "lastNightAvg": 41,
    "lastNight5MinHigh": 57,
    "baseline": {
      "lowUpper": 38,
      "balancedLow": 40,
      "balancedUpper": 52,
      "markerValue": 0.5416565
    },
    "status": "BALANCED",
    "feedbackPhrase": "HRV_BALANCED_2",
    "createTimeStamp": "2026-01-08T09:26:49.772"
  },
  "hrvReadings": [
    {
      "hrvValue": 51,
      "readingTimeGMT": "2026-01-07T22:17:45.0",
      "readingTimeLocal": "2026-01-08T01:17:45.0"
    },
    {
      "hrvValue": 50,
      "readingTimeGMT": "2026-01-07T22:22:45.0",
      "readingTimeLocal": "2026-01-08T01:22:45.0"
    },
    {
      "hrvValue": 38,
      "readingTimeGMT": "2026-01-07T22:27:45.0",
      "readingTimeLocal": "2026-01-08T01:27:45.0"
    },
    {
      "hrvValue": 40,
      "readingTimeGMT": "2026-01-07T22:32:45.0",
      "readingTimeLocal": "2026-01-08T01:32:45.0"
    },
    {
      "hrvValue": 41,
      "readingTimeGMT": "2026-01-07T22:37:45.0",
      "readingTimeLocal": "2026-01-08T01:37:45.0"
    },
    {
      "hrvValue": 39,
      "readingTimeGMT": "2026-01-07T22:42:45.0",
      "readingTimeLocal": "2026-01-08T01:42:45.0"
    },
    {
      "hrvValue": 47,
      "readingTimeGMT": "2026-01-07T22:47:45.0",
      "readingTimeLocal": "2026-01-08T01:47:45.0"
    },
    {
      "hrvValue": 38,
      "readingTimeGMT": "2026-01-07T22:52:45.0",
      "readingTimeLocal": "2026-01-08T01:52:45.0"
    },
    {
      "hrvValue": 44,
      "readingTimeGMT": "2026-01-07T22:57:45.0",
      "readingTimeLocal": "2026-01-08T01:57:45.0"
    },
    {
      "hrvValue": 50,
      "readingTimeGMT": "2026-01-07T23:02:45.0",
      "readingTimeLocal": "2026-01-08T02:02:45.0"
    },
    {
      "hrvValue": 41,
      "readingTimeGMT": "2026-01-07T23:07:45.0",
      "readingTimeLocal": "2026-01-08T02:07:45.0"
    },
    {
      "hrvValue": 35,
      "readingTimeGMT": "2026-01-07T23:12:45.0",
      "readingTimeLocal": "2026-01-08T02:12:45.0"
    },
    {
      "hrvValue": 31,
      "readingTimeGMT": "2026-01-07T23:17:45.0",
      "readingTimeLocal": "2026-01-08T02:17:45.0"
    },
    {
      "hrvValue": 36,
      "readingTimeGMT": "2026-01-07T23:22:45.0",
      "readingTimeLocal": "2026-01-08T02:22:45.0"
    },
    {
      "hrvValue": 31,
      "readingTimeGMT": "2026-01-07T23:27:45.0",
      "readingTimeLocal": "2026-01-08T02:27:45.0"
    },
    {
      "hrvValue": 31,
      "readingTimeGMT": "2026-01-07T23:32:45.0",
      "readingTimeLocal": "2026-01-08T02:32:45.0"
    },
    {
      "hrvValue": 37,
      "readingTimeGMT": "2026-01-07T23:37:45.0",
      "readingTimeLocal": "2026-01-08T02:37:45.0"
    },
    {
      "hrvValue": 43,
      "readingTimeGMT": "2026-01-07T23:42:45.0",
      "readingTimeLocal": "2026-01-08T02:42:45.0"
    },
    {
      "hrvValue": 57,
      "readingTimeGMT": "2026-01-07T23:47:45.0",
      "readingTimeLocal": "2026-01-08T02:47:45.0"
    },
    {
      "hrvValue": 52,
      "readingTimeGMT": "2026-01-07T23:52:45.0",
      "readingTimeLocal": "2026-01-08T02:52:45.0"
    },
    {
      "hrvValue": 56,
      "readingTimeGMT": "2026-01-07T23:57:45.0",
      "readingTimeLocal": "2026-01-08T02:57:45.0"
    },
    {
      "hrvValue": 51,
      "readingTimeGMT": "2026-01-08T00:02:45.0",
      "readingTimeLocal": "2026-01-08T03:02:45.0"
    },
    {
      "hrvValue": 51,
      "readingTimeGMT": "2026-01-08T00:07:45.0",
      "readingTimeLocal": "2026-01-08T03:07:45.0"
    },
    {
      "hrvValue": 48,
      "readingTimeGMT": "2026-01-08T00:12:45.0",
      "readingTimeLocal": "2026-01-08T03:12:45.0"
    },
    {
      "hrvValue": 40,
      "readingTimeGMT": "2026-01-08T00:17:45.0",
      "readingTimeLocal": "2026-01-08T03:17:45.0"
    },
    {
      "hrvValue": 37,
      "readingTimeGMT": "2026-01-08T00:22:45.0",
      "readingTimeLocal": "2026-01-08T03:22:45.0"
    },
    {
      "hrvValue": 41,
      "readingTimeGMT": "2026-01-08T00:27:45.0",
      "readingTimeLocal": "2026-01-08T03:27:45.0"
    },
    {
      "hrvValue": 42,
      "readingTimeGMT": "2026-01-08T00:32:45.0",
      "readingTimeLocal": "2026-01-08T03:32:45.0"
    },
    {
      "hrvValue": 40,
      "readingTimeGMT": "2026-01-08T00:37:45.0",
      "readingTimeLocal": "2026-01-08T03:37:45.0"
    },
    {
      "hrvValue": 43,
      "readingTimeGMT": "2026-01-08T00:42:45.0",
      "readingTimeLocal": "2026-01-08T03:42:45.0"
    },
    {
      "hrvValue": 46,
      "readingTimeGMT": "2026-01-08T00:47:45.0",
      "readingTimeLocal": "2026-01-08T03:47:45.0"
    },
    {
      "hrvValue": 37,
      "readingTimeGMT": "2026-01-08T00:52:45.0",
      "readingTimeLocal": "2026-01-08T03:52:45.0"
    },
    {
      "hrvValue": 37,
      "readingTimeGMT": "2026-01-08T00:57:45.0",
      "readingTimeLocal": "2026-01-08T03:57:45.0"
    },
    {
      "hrvValue": 42,
      "readingTimeGMT": "2026-01-08T01:02:45.0",
      "readingTimeLocal": "2026-01-08T04:02:45.0"
    },
    {
      "hrvValue": 40,
      "readingTimeGMT": "2026-01-08T01:07:45.0",
      "readingTimeLocal": "2026-01-08T04:07:45.0"
    },
    {
      "hrvValue": 41,
      "readingTimeGMT": "2026-01-08T01:12:45.0",
      "readingTimeLocal": "2026-01-08T04:12:45.0"
    },
    {
      "hrvValue": 42,
      "readingTimeGMT": "2026-01-08T01:17:45.0",
      "readingTimeLocal": "2026-01-08T04:17:45.0"
    },
    {
      "hrvValue": 37,
      "readingTimeGMT": "2026-01-08T01:22:45.0",
      "readingTimeLocal": "2026-01-08T04:22:45.0"
    },
    {
      "hrvValue": 29,
      "readingTimeGMT": "2026-01-08T01:27:45.0",
      "readingTimeLocal": "2026-01-08T04:27:45.0"
    },
    {
      "hrvValue": 26,
      "readingTimeGMT": "2026-01-08T01:32:45.0",
      "readingTimeLocal": "2026-01-08T04:32:45.0"
    },
    {
      "hrvValue": 27,
      "readingTimeGMT": "2026-01-08T01:37:45.0",
      "readingTimeLocal": "2026-01-08T04:37:45.0"
    },
    {
      "hrvValue": 24,
      "readingTimeGMT": "2026-01-08T01:42:45.0",
      "readingTimeLocal": "2026-01-08T04:42:45.0"
    },
    {
      "hrvValue": 33,
      "readingTimeGMT": "2026-01-08T01:47:45.0",
      "readingTimeLocal": "2026-01-08T04:47:45.0"
    },
    {
      "hrvValue": 33,
      "readingTimeGMT": "2026-01-08T01:52:45.0",
      "readingTimeLocal": "2026-01-08T04:52:45.0"
    },
    {
      "hrvValue": 38,
      "readingTimeGMT": "2026-01-08T01:57:45.0",
      "readingTimeLocal": "2026-01-08T04:57:45.0"
    },
    {
      "hrvValue": 38,
      "readingTimeGMT": "2026-01-08T02:02:45.0",
      "readingTimeLocal": "2026-01-08T05:02:45.0"
    },
    {
      "hrvValue": 41,
      "readingTimeGMT": "2026-01-08T02:07:45.0",
      "readingTimeLocal": "2026-01-08T05:07:45.0"
    },
    {
      "hrvValue": 46,
      "readingTimeGMT": "2026-01-08T02:12:45.0",
      "readingTimeLocal": "2026-01-08T05:12:45.0"
    },
    {
      "hrvValue": 42,
      "readingTimeGMT": "2026-01-08T02:17:45.0",
      "readingTimeLocal": "2026-01-08T05:17:45.0"
    },
    {
      "hrvValue": 37,
      "readingTimeGMT": "2026-01-08T02:22:45.0",
      "readingTimeLocal": "2026-01-08T05:22:45.0"
    },
    {
      "hrvValue": 35,
      "readingTimeGMT": "2026-01-08T02:27:45.0",
      "readingTimeLocal": "2026-01-08T05:27:45.0"
    },
    {
      "hrvValue": 37,
      "readingTimeGMT": "2026-01-08T02:32:45.0",
      "readingTimeLocal": "2026-01-08T05:32:45.0"
    },
    {
      "hrvValue": 35,
      "readingTimeGMT": "2026-01-08T02:37:45.0",
      "readingTimeLocal": "2026-01-08T05:37:45.0"
    },
    {
      "hrvValue": 35,
      "readingTimeGMT": "2026-01-08T02:42:45.0",
      "readingTimeLocal": "2026-01-08T05:42:45.0"
    },
    {
      "hrvValue": 34,
      "readingTimeGMT": "2026-01-08T02:47:45.0",
      "readingTimeLocal": "2026-01-08T05:47:45.0"
    },
    {
      "hrvValue": 34,
      "readingTimeGMT": "2026-01-08T02:52:45.0",
      "readingTimeLocal": "2026-01-08T05:52:45.0"
    },
    {
      "hrvValue": 49,
      "readingTimeGMT": "2026-01-08T02:57:45.0",
      "readingTimeLocal": "2026-01-08T05:57:45.0"
    },
    {
      "hrvValue": 57,
      "readingTimeGMT": "2026-01-08T03:02:45.0",
      "readingTimeLocal": "2026-01-08T06:02:45.0"
    },
    {
      "hrvValue": 41,
      "readingTimeGMT": "2026-01-08T03:07:45.0",
      "readingTimeLocal": "2026-01-08T06:07:45.0"
    },
    {
      "hrvValue": 49,
      "readingTimeGMT": "2026-01-08T03:12:45.0",
      "readingTimeLocal": "2026-01-08T06:12:45.0"
    },
    {
      "hrvValue": 44,
      "readingTimeGMT": "2026-01-08T03:17:45.0",
      "readingTimeLocal": "2026-01-08T06:17:45.0"
    },
    {
      "hrvValue": 44,
      "readingTimeGMT": "2026-01-08T03:22:45.0",
      "readingTimeLocal": "2026-01-08T06:22:45.0"
    },
    {
      "hrvValue": 48,
      "readingTimeGMT": "2026-01-08T03:27:45.0",
      "readingTimeLocal": "2026-01-08T06:27:45.0"
    },
    {
      "hrvValue": 40,
      "readingTimeGMT": "2026-01-08T03:32:45.0",
      "readingTimeLocal": "2026-01-08T06:32:45.0"
    },
    {
      "hrvValue": 39,
      "readingTimeGMT": "2026-01-08T03:37:45.0",
      "readingTimeLocal": "2026-01-08T06:37:45.0"
    },
    {
      "hrvValue": 55,
      "readingTimeGMT": "2026-01-08T03:42:45.0",
      "readingTimeLocal": "2026-01-08T06:42:45.0"
    },
    {
      "hrvValue": 41,
      "readingTimeGMT": "2026-01-08T03:47:45.0",
      "readingTimeLocal": "2026-01-08T06:47:45.0"
    },
    {
      "hrvValue": 47,
      "readingTimeGMT": "2026-01-08T03:52:45.0",
      "readingTimeLocal": "2026-01-08T06:52:45.0"
    },
    {
      "hrvValue": 53,
      "readingTimeGMT": "2026-01-08T03:57:45.0",
      "readingTimeLocal": "2026-01-08T06:57:45.0"
    },
    {
      "hrvValue": 43,
      "readingTimeGMT": "2026-01-08T04:02:45.0",
      "readingTimeLocal": "2026-01-08T07:02:45.0"
    },
    {
      "hrvValue": 50,
      "readingTimeGMT": "2026-01-08T04:07:45.0",
      "readingTimeLocal": "2026-01-08T07:07:45.0"
    },
    {
      "hrvValue": 44,
      "readingTimeGMT": "2026-01-08T04:12:45.0",
      "readingTimeLocal": "2026-01-08T07:12:45.0"
    },
    {
      "hrvValue": 42,
      "readingTimeGMT": "2026-01-08T04:17:45.0",
      "readingTimeLocal": "2026-01-08T07:17:45.0"
    },
    {
      "hrvValue": 45,
      "readingTimeGMT": "2026-01-08T04:22:45.0",
      "readingTimeLocal": "2026-01-08T07:22:45.0"
    },
    {
      "hrvValue": 48,
      "readingTimeGMT": "2026-01-08T04:27:45.0",
      "readingTimeLocal": "2026-01-08T07:27:45.0"
    },
    {
      "hrvValue": 45,
      "readingTimeGMT": "2026-01-08T04:32:45.0",
      "readingTimeLocal": "2026-01-08T07:32:45.0"
    },
    {
      "hrvValue": 45,
      "readingTimeGMT": "2026-01-08T04:37:45.0",
      "readingTimeLocal": "2026-01-08T07:37:45.0"
    },
    {
      "hrvValue": 40,
      "readingTimeGMT": "2026-01-08T04:42:45.0",
      "readingTimeLocal": "2026-01-08T07:42:45.0"
    },
    {
      "hrvValue": 40,
      "readingTimeGMT": "2026-01-08T04:47:45.0",
      "readingTimeLocal": "2026-01-08T07:47:45.0"
    },
    {
      "hrvValue": 50,
      "readingTimeGMT": "2026-01-08T04:52:45.0",
      "readingTimeLocal": "2026-01-08T07:52:45.0"
    },
    {
      "hrvValue": 43,
      "readingTimeGMT": "2026-01-08T04:57:45.0",
      "readingTimeLocal": "2026-01-08T07:57:45.0"
    },
    {
      "hrvValue": 47,
      "readingTimeGMT": "2026-01-08T05:02:45.0",
      "readingTimeLocal": "2026-01-08T08:02:45.0"
    },
    {
      "hrvValue": 47,
      "readingTimeGMT": "2026-01-08T05:07:45.0",
      "readingTimeLocal": "2026-01-08T08:07:45.0"
    },
    {
      "hrvValue": 43,
      "readingTimeGMT": "2026-01-08T05:12:45.0",
      "readingTimeLocal": "2026-01-08T08:12:45.0"
    },
    {
      "hrvValue": 46,
      "readingTimeGMT": "2026-01-08T05:17:45.0",
      "readingTimeLocal": "2026-01-08T08:17:45.0"
    },
    {
      "hrvValue": 42,
      "readingTimeGMT": "2026-01-08T05:22:45.0",
      "readingTimeLocal": "2026-01-08T08:22:45.0"
    },
    {
      "hrvValue": 42,
      "readingTimeGMT": "2026-01-08T05:27:45.0",
      "readingTimeLocal": "2026-01-08T08:27:45.0"
    },
    {
      "hrvValue": 46,
      "readingTimeGMT": "2026-01-08T05:32:45.0",
      "readingTimeLocal": "2026-01-08T08:32:45.0"
    },
    {
      "hrvValue": 53,
      "readingTimeGMT": "2026-01-08T05:37:45.0",
      "readingTimeLocal": "2026-01-08T08:37:45.0"
    },
    {
      "hrvValue": 50,
      "readingTimeGMT": "2026-01-08T05:42:45.0",
      "readingTimeLocal": "2026-01-08T08:42:45.0"
    },
    {
      "hrvValue": 37,
      "readingTimeGMT": "2026-01-08T05:47:45.0",
      "readingTimeLocal": "2026-01-08T08:47:45.0"
    },
    {
      "hrvValue": 52,
      "readingTimeGMT": "2026-01-08T05:52:45.0",
      "readingTimeLocal": "2026-01-08T08:52:45.0"
    },
    {
      "hrvValue": 40,
      "readingTimeGMT": "2026-01-08T05:57:45.0",
      "readingTimeLocal": "2026-01-08T08:57:45.0"
    },
    {
      "hrvValue": 50,
      "readingTimeGMT": "2026-01-08T06:02:45.0",
      "readingTimeLocal": "2026-01-08T09:02:45.0"
    },
    {
      "hrvValue": 38,
      "readingTimeGMT": "2026-01-08T06:07:45.0",
      "readingTimeLocal": "2026-01-08T09:07:45.0"
    },
    {
      "hrvValue": 44,
      "readingTimeGMT": "2026-01-08T06:12:45.0",
      "readingTimeLocal": "2026-01-08T09:12:45.0"
    },
    {
      "hrvValue": 37,
      "readingTimeGMT": "2026-01-08T06:17:45.0",
      "readingTimeLocal": "2026-01-08T09:17:45.0"
    },
    {
      "hrvValue": 48,
      "readingTimeGMT": "2026-01-08T06:22:45.0",
      "readingTimeLocal": "2026-01-08T09:22:45.0"
    },
    {
      "hrvValue": 43,
      "readingTimeGMT": "2026-01-08T06:27:45.0",
      "readingTimeLocal": "2026-01-08T09:27:45.0"
    },
    {
      "hrvValue": 36,
      "readingTimeGMT": "2026-01-08T06:32:45.0",
      "readingTimeLocal": "2026-01-08T09:32:45.0"
    },
    {
      "hrvValue": 31,
      "readingTimeGMT": "2026-01-08T06:37:45.0",
      "readingTimeLocal": "2026-01-08T09:37:45.0"
    },
    {
      "hrvValue": 38,
      "readingTimeGMT": "2026-01-08T06:42:45.0",
      "readingTimeLocal": "2026-01-08T09:42:45.0"
    },
    {
      "hrvValue": 42,
      "readingTimeGMT": "2026-01-08T06:47:45.0",
      "readingTimeLocal": "2026-01-08T09:47:45.0"
    },
    {
      "hrvValue": 32,
      "readingTimeGMT": "2026-01-08T06:52:45.0",
      "readingTimeLocal": "2026-01-08T09:52:45.0"
    },
    {
      "hrvValue": 43,
      "readingTimeGMT": "2026-01-08T06:57:45.0",
      "readingTimeLocal": "2026-01-08T09:57:45.0"
    },
    {
      "hrvValue": 37,
      "readingTimeGMT": "2026-01-08T07:02:45.0",
      "readingTimeLocal": "2026-01-08T10:02:45.0"
    },
    {
      "hrvValue": 34,
      "readingTimeGMT": "2026-01-08T07:07:45.0",
      "readingTimeLocal": "2026-01-08T10:07:45.0"
    },
    {
      "hrvValue": 38,
      "readingTimeGMT": "2026-01-08T07:12:45.0",
      "readingTimeLocal": "2026-01-08T10:12:45.0"
    },
    {
      "hrvValue": 36,
      "readingTimeGMT": "2026-01-08T07:17:45.0",
      "readingTimeLocal": "2026-01-08T10:17:45.0"
    },
    {
      "hrvValue": 36,
      "readingTimeGMT": "2026-01-08T07:22:45.0",
      "readingTimeLocal": "2026-01-08T10:22:45.0"
    },
    {
      "hrvValue": 37,
      "readingTimeGMT": "2026-01-08T07:27:45.0",
      "readingTimeLocal": "2026-01-08T10:27:45.0"
    },
    {
      "hrvValue": 43,
      "readingTimeGMT": "2026-01-08T07:32:45.0",
      "readingTimeLocal": "2026-01-08T10:32:45.0"
    },
    {
      "hrvValue": 41,
      "readingTimeGMT": "2026-01-08T07:37:45.0",
      "readingTimeLocal": "2026-01-08T10:37:45.0"
    },
    {
      "hrvValue": 42,
      "readingTimeGMT": "2026-01-08T07:42:45.0",
      "readingTimeLocal": "2026-01-08T10:42:45.0"
    },
    {
      "hrvValue": 29,
      "readingTimeGMT": "2026-01-08T07:47:45.0",
      "readingTimeLocal": "2026-01-08T10:47:45.0"
    },
    {
      "hrvValue": 35,
      "readingTimeGMT": "2026-01-08T07:52:45.0",
      "readingTimeLocal": "2026-01-08T10:52:45.0"
    },
    {
      "hrvValue": 47,
      "readingTimeGMT": "2026-01-08T07:57:45.0",
      "readingTimeLocal": "2026-01-08T10:57:45.0"
    },
    {
      "hrvValue": 44,
      "readingTimeGMT": "2026-01-08T08:02:45.0",
      "readingTimeLocal": "2026-01-08T11:02:45.0"
    },
    {
      "hrvValue": 42,
      "readingTimeGMT": "2026-01-08T08:07:45.0",
      "readingTimeLocal": "2026-01-08T11:07:45.0"
    },
    {
      "hrvValue": 47,
      "readingTimeGMT": "2026-01-08T08:12:45.0",
      "readingTimeLocal": "2026-01-08T11:12:45.0"
    },
    {
      "hrvValue": 43,
      "readingTimeGMT": "2026-01-08T08:17:45.0",
      "readingTimeLocal": "2026-01-08T11:17:45.0"
    },
    {
      "hrvValue": 44,
      "readingTimeGMT": "2026-01-08T08:22:45.0",
      "readingTimeLocal": "2026-01-08T11:22:45.0"
    },
    {
      "hrvValue": 44,
      "readingTimeGMT": "2026-01-08T08:27:45.0",
      "readingTimeLocal": "2026-01-08T11:27:45.0"
    },
    {
      "hrvValue": 43,
      "readingTimeGMT": "2026-01-08T08:32:45.0",
      "readingTimeLocal": "2026-01-08T11:32:45.0"
    },
    {
      "hrvValue": 44,
      "readingTimeGMT": "2026-01-08T08:37:45.0",
      "readingTimeLocal": "2026-01-08T11:37:45.0"
    },
    {
      "hrvValue": 44,
      "readingTimeGMT": "2026-01-08T08:42:45.0",
      "readingTimeLocal": "2026-01-08T11:42:45.0"
    },
    {
      "hrvValue": 44,
      "readingTimeGMT": "2026-01-08T08:47:45.0",
      "readingTimeLocal": "2026-01-08T11:47:45.0"
    },
    {
      "hrvValue": 41,
      "readingTimeGMT": "2026-01-08T08:52:45.0",
      "readingTimeLocal": "2026-01-08T11:52:45.0"
    },
    {
      "hrvValue": 38,
      "readingTimeGMT": "2026-01-08T08:57:45.0",
      "readingTimeLocal": "2026-01-08T11:57:45.0"
    },
    {
      "hrvValue": 42,
      "readingTimeGMT": "2026-01-08T09:02:45.0",
      "readingTimeLocal": "2026-01-08T12:02:45.0"
    },
    {
      "hrvValue": 47,
      "readingTimeGMT": "2026-01-08T09:07:45.0",
      "readingTimeLocal": "2026-01-08T12:07:45.0"
    },
    {
      "hrvValue": 39,
      "readingTimeGMT": "2026-01-08T09:12:45.0",
      "readingTimeLocal": "2026-01-08T12:12:45.0"
    },
    {
      "hrvValue": 39,
      "readingTimeGMT": "2026-01-08T09:17:45.0",
      "readingTimeLocal": "2026-01-08T12:17:45.0"
    }
  ],
  "startTimestampGMT": "2026-01-07T22:14:12.0",
  "endTimestampGMT": "2026-01-08T09:17:45.0",
  "startTimestampLocal": "2026-01-08T01:14:12.0",
  "endTimestampLocal": "2026-01-08T12:17:45.0",
  "sleepStartTimestampGMT": "2026-01-07T22:14:12.0",
  "sleepEndTimestampGMT": "2026-01-08T09:21:34.0",
  "sleepStartTimestampLocal": "2026-01-08T01:14:12.0",
  "sleepEndTimestampLocal": "2026-01-08T12:21:34.0"
}